users_auth/__init__.py
users_auth/admin.py
users_auth/apps.py
users_auth/db_router.py
users_auth/models.py
users_auth/serializers.py
users_auth/tests.py
users_auth/validators.py
users_auth/views.py
users_auth/migrations/0001_initial.py
users_auth/migrations/__init__.py
qt_users_service-0.6.dist-info/LICENSE
qt_users_service-0.6.dist-info/METADATA
qt_users_service-0.6.dist-info/WHEEL
qt_users_service-0.6.dist-info/top_level.txt
qt_users_service-0.6.dist-info/RECORD
